symbolize/__init__.py
symbolize-0.0.1.dist-info/METADATA
symbolize-0.0.1.dist-info/WHEEL
symbolize-0.0.1.dist-info/RECORD
