Metadata-Version: 2.4
Name: symbolize
Version: 0.0.1
Summary: Core DSL architecture + demo First-Order-Logic DSL
Author: Ezra Keshet
Requires-Python: >=3.11
Requires-Dist: graphviz>=0.20
Requires-Dist: svgling>=0.3
